sales.py
settings.py
alexrasero_sales-0.0.1.dist-info/METADATA
alexrasero_sales-0.0.1.dist-info/WHEEL
alexrasero_sales-0.0.1.dist-info/RECORD
